{
  "$schema": "http://json-schema.org/draft-07/schema#",
  "$id": "response/admin_list_account_transfers",
  "title": "Admin list account transfers response",
  "type": "object",
  "properties": {
    "status_code": {
      "title": "Status code",
      "type": "string"
    },
    "account_transfers": {
      "title": "Account transfers",
      "type": "array",
      "items": {
        "title": "Account transfer",
        "type": "object",
        "properties": {
          "account_owner_id": {
            "title": "Account owner id",
            "type": [
              "string",
              "null"
            ]
          },
          "account_owner_email": {
            "title": "Account owner email",
            "type": [
              "string",
              "null"
            ]
          },
          "deposit_amount": {
            "title": "Deposit amount",
            "type": [
              "null",
              "integer"
            ]
          },
          "withdrawal_amount": {
            "title": "Withdrawal amount",
            "type": [
              "null",
              "integer"
            ]
          },
          "transferred_at": {
            "title": "Transferred_at",
            "type": [
              "null",
              "string"
            ]
          },
          "type": {
            "title": "Transfer type",
            "type": [
              "null",
              "string"
            ]
          },
          "reason": {
            "title": "Transfer reason",
            "type": [
              "null",
              "string"
            ]
          },
          "employee_transferrer_id": {
            "title": "Employee transferrer id",
            "type": [
              "null",
              "string"
            ]
          },
          "employee_transferrer_email": {
            "title": "Employee transferrer email",
            "type": [
              "null",
              "string"
            ]
          },
          "user_subscr_airport_from_name": {
            "title": "User subscription airport from name",
            "type": [
              "null",
              "string"
            ]
          },
          "user_subscr_airport_to_name": {
            "title": "User subscription airport to name",
            "type": [
              "null",
              "string"
            ]
          },
          "user_subscr_date_from": {
            "title": "User subscription date from",
            "type": [
              "null",
              "string"
            ]
          },
          "user_subscr_date_to": {
            "title": "User subscription date to",
            "type": [
              "null",
              "string"
            ]
          },
          "subscr_airport_from_name": {
            "title": "Subscription airport from name",
            "type": [
              "null",
              "string"
            ]
          },
          "subscr_airport_to_name": {
            "title": "Subscription airport to name",
            "type": [
              "null",
              "string"
            ]
          },
          "fetch_time": {
            "title": "Fetch time",
            "type": [
              "null",
              "string"
            ]
          },
          "grouped_amount": {
            "title": "Grouped amount",
            "type": [
              "null",
              "string"
            ]
          }
        }
      }
    },
    "active_columns": {
      "title": "Active columns",
      "type": "array",
      "items": {
        "title": "Active column",
        "type": "string"
      }
    }
  },
  "required": [
    "status_code",
    "account_transfers",
    "active_columns"
  ]
}
